tweepymashup/__init__.py
tweepymashup/api.py
tweepymashup/auth.py
tweepymashup/binder.py
tweepymashup/cache.py
tweepymashup/cursor.py
tweepymashup/error.py
tweepymashup/models.py
tweepymashup/parsers.py
tweepymashup/streaming.py
tweepymashup/utils.py
tweepymashup-1.0.7.dist-info/LICENSE
tweepymashup-1.0.7.dist-info/METADATA
tweepymashup-1.0.7.dist-info/WHEEL
tweepymashup-1.0.7.dist-info/top_level.txt
tweepymashup-1.0.7.dist-info/zip-safe
tweepymashup-1.0.7.dist-info/RECORD
