Metadata-Version: 2.1
Name: tweepymashup
Version: 1.0.7
Summary: Multi-Auth handling,Twitter library for python
Home-page: https://github.com/oblockton/tweepy_fix
Author: O.G-Joshua Roesslein Remix-Nirg Mashup-oblockton
Author-email: tweepy@googlegroups.com
License: MIT
Keywords: twitter library
Platform: UNKNOWN
Classifier: Development Status :: 5 - Production/Stable
Classifier: Topic :: Software Development :: Libraries
Classifier: License :: OSI Approved :: MIT License
Classifier: Operating System :: OS Independent
Classifier: Programming Language :: Python
Classifier: Programming Language :: Python :: 3
Classifier: Programming Language :: Python :: 3.5
Classifier: Programming Language :: Python :: 3.6
Classifier: Programming Language :: Python :: 3.7
Requires-Python: >=2.7, !=3.0.*, !=3.1.*, !=3.2.*, !=3.3.*, !=3.4.*
Requires-Dist: PySocks (>=1.5.7)
Requires-Dist: requests (>=2.11.1)
Requires-Dist: requests-oauthlib (>=0.7.0)
Requires-Dist: six (>=1.10.0)
